{"\/":2049,"\/new-page":16,"\/new-new":5,"\/new-page\/blog":1,"\/index":13,"\/blah":34,"\/info":205,"\/work":489,"\/blog":4,"\/work\/project1":28,"\/news":224,"\/work\/project2":60,"\/work\/project-3":35,"\/work\/project3":140,"\/work2":20,"\/selected":22,"\/work\/selected":1526,"\/work\/all":560,"\/work\/another_project":8,"\/work\/selected\/work\/project2":1,"\/work\/selected\/work\/project3":2,"\/work\/thin_table_2":48,"\/work\/bow_tie_table":339,"\/work\/a-table":152,"\/work\/thin_chair":48,"\/work\/thin_table_1":34,"\/work\/square_table":31,"\/work\/trace-table":39,"\/work\/floating-stair_1":12,"\/work\/photobooth":18,"\/work\/oxide-workstation":14,"\/work\/pomegranate_light":9}